simpleafier/__init__.py
simpleafier/__main__.py
simpleafier-0.1.4.dist-info/licenses/LICENSE.txt
tests/__init__.py
tests/test_simponly.py
simpleafier-0.1.4.dist-info/METADATA
simpleafier-0.1.4.dist-info/WHEEL
simpleafier-0.1.4.dist-info/top_level.txt
simpleafier-0.1.4.dist-info/RECORD
