Metadata-Version: 2.4
Name: Simpleafier
Version: 0.1.4
Summary: A command line tool to help improve the quality of Lean code by converting any "simp" to "simp only".
Home-page: https://github.com/mrigankpawagi/Simpleafier
Author: Mrigank Pawagi
Author-email: Mrigank Pawagi <mrigankpawagi@gmail.com>
Project-URL: Homepage, https://github.com/mrigankpawagi/Simpleafier
Classifier: Programming Language :: Python :: 3
Classifier: Operating System :: POSIX :: Linux
Requires-Python: >=3.6
License-File: LICENSE.txt
Dynamic: license-file
